megaram/hw/rtl/bank_switch.v
/* bank_switch.v — Combinational bank-number decoder for ATARI XL/XE memory expansions.
 *
 * Mirrors the bank_lut[] table from abex-megaram/megaram/src/main.c.
 * All eight expansion types are supported; the active type is selected by
 * the three DIP-switch bits on conf[2:0].
 *
 * Outputs:
 *   bank[5:0]  — 6-bit bank index (0–63); meaningless when active=0
 *   active     — 1 when the external SRAM should respond to the current cycle
 *
 * Conditions for active=1 (in addition to expansion-specific checks):
 *   - pbctl_crb2 must be 1 (PBCTL bit 2 set → output register mode;
 *     if 0 the $D301 access goes to the DDR, not PORTB)
 */
`default_nettype none

module bank_switch (
    input  wire [7:0] portb,        /* current PORTB value                  */
    input  wire       pbctl_crb2,   /* PBCTL bit 2: 1 = output register mode */
    input  wire [2:0] conf,         /* DIP-switch expansion type select      */
    output wire [5:0] bank,         /* bank index                            */
    output wire       active         /* 1 = external SRAM should respond      */
);
    /* Expansion-type codes — match EXPANSION_TYPE_* in main.h */
    localparam [2:0]
        EXP_130XE          = 3'd0,  /* 64K   extended  (4 banks × 16K)       */
        EXP_192K           = 3'd1,  /* 128K  extended  (8 banks × 16K)       */
        EXP_256K_RAMBO     = 3'd2,  /* 256K  RAMBO     (16 banks × 16K)      */
        EXP_320K           = 3'd3,  /* 256K  extended  (16 banks × 16K)      */
        EXP_320K_COMPYSHOP = 3'd4,  /* 256K  Compyshop (16 banks × 16K)      */
        EXP_576K_MOD       = 3'd5,  /* 512K  Mod       (32 banks × 16K)      */
        EXP_576K_COMPYSHOP = 3'd6,  /* 512K  Compyshop (32 banks × 16K)      */
        EXP_1088K_MOD      = 3'd7;  /* 1024K Mod       (64 banks × 16K)      */

    reg [5:0] bank_r;
    reg       active_r;

    always @(*) begin
        bank_r   = 6'd0;
        active_r = 1'b0;

        if (pbctl_crb2) begin
            case (conf)

                /* ----------------------------------------------------------
                 * 130XE: CBE (bit 4) = 0 enables CPU access to extended RAM.
                 * VBE (bit 5) is for ANTIC DMA only, never visible on PHI2.
                 * Bank bits: portb[3:2] → 4 banks
                 */
                EXP_130XE:
                    if (!portb[4]) begin
                        bank_r   = {4'b0, portb[3:2]};
                        active_r = 1'b1;
                    end

                /* ----------------------------------------------------------
                 * Compyshop 192K: same CBE check; adds bit 6 for 8 banks.
                 * Bank bits: {portb[6], portb[3:2]}
                 */
                EXP_192K:
                    if (!portb[4]) begin
                        bank_r   = {3'b0, portb[6], portb[3:2]};
                        active_r = 1'b1;
                    end

                /* ----------------------------------------------------------
                 * RAMBO 256K: RAME (bit 4) = 0 → RAMBO active (all 16 banks).
                 *             RAME (bit 4) = 1 → Atari internal RAM responds.
                 * Bank bits: {portb[6:5], portb[3:2]} → 16 banks
                 */
                EXP_256K_RAMBO:
                    if (!portb[4]) begin
                        bank_r   = {2'b0, portb[6:5], portb[3:2]};
                        active_r = 1'b1;
                    end

                /* ----------------------------------------------------------
                 * 320K (standard RAMBO 320K): same bank formula as 256K_RAMBO.
                 * Bank bits: {portb[6:5], portb[3:2]} → 16 banks
                 */
                EXP_320K:
                    if (!portb[4]) begin
                        bank_r   = {2'b0, portb[6:5], portb[3:2]};
                        active_r = 1'b1;
                    end

                /* ----------------------------------------------------------
                 * Compyshop 320K: combined enable (bit5 AND bit4 must not
                 * both be set).  Bank bits: {portb[7:6], portb[3:2]}
                 */
                EXP_320K_COMPYSHOP:
                    if (portb[5:4] != 2'b11) begin
                        bank_r   = {2'b0, portb[7:6], portb[3:2]};
                        active_r = 1'b1;
                    end

                /* ----------------------------------------------------------
                 * 576K Mod: bit 4 = 0 enables; adds bits 1,5,6 for 32 banks.
                 * Bank bits: {portb[6:5], portb[3:1]} → 32 banks
                 */
                EXP_576K_MOD:
                    if (!portb[4]) begin
                        bank_r   = {1'b0, portb[6:5], portb[3:1]};
                        active_r = 1'b1;
                    end

                /* ----------------------------------------------------------
                 * Compyshop 576K: bit 4 = 0 enables; adds bits 1,6,7.
                 * Bank bits: {portb[7:6], portb[3:1]} → 32 banks
                 */
                EXP_576K_COMPYSHOP:
                    if (!portb[4]) begin
                        bank_r   = {1'b0, portb[7:6], portb[3:1]};
                        active_r = 1'b1;
                    end

                /* ----------------------------------------------------------
                 * 1088K Mod: bit 4 = 0 enables; uses bits 1-3 and 5-7.
                 * Bank bits: {portb[7:5], portb[3:1]} → 64 banks (1MB SRAM)
                 */
                EXP_1088K_MOD:
                    if (!portb[4]) begin
                        bank_r   = {portb[7:5], portb[3:1]};
                        active_r = 1'b1;
                    end

                default: begin
                    bank_r   = 6'd0;
                    active_r = 1'b0;
                end
            endcase
        end
    end

    assign bank   = bank_r;
    assign active = active_r;

endmodule

megaram/hw/rtl/portb_emu.v
/* portb_emu.v — Minimal PIA 6520 emulation for ATARI XL/XE PORTB bank-switching.
 *
 * Only the Port-B side of the 6520 is emulated (the STM32 firmware does the
 * same).  The relevant registers, using the Atari address mapping where A0 is
 * wired to RS1 and A1 to RS0 (i.e. reversed from the generic 6520 spec):
 *
 *   $D301 (addr[1:0]=01): PORTB output register  OR  DDRB
 *                         selected by pbctl[2] (CRB-2 / DDR):
 *                           pbctl[2]=1 → output register (PORTB)
 *                           pbctl[2]=0 → data-direction  (DDRB)
 *   $D303 (addr[1:0]=11): PBCTL (Port B Control Register)
 *
 * Both addresses mirror every 4 bytes throughout $D300–$D3FF.
 *
 * Reset / power-on values matching the STM32 firmware:
 *   PORTB = 0xFF  (all bits output, memory-map = Atari internal + OS ROM)
 *   PBCTL = 0x00  (DDR mode initially, until OS sets bit 2)
 *   DDRB  = 0x00
 *
 * Writes are latched on the FALLING edge of PHI2; the 6502 guarantees data
 * hold past the falling edge, so this is safe at 1.79 MHz.
 *
 * NOTE: PHI2 must be routed through a global clock buffer on the target FPGA
 * (e.g. SB_GB on iCE40, CLKDIVF/CLKBUF on ECP5) to avoid hold-time issues.
 */
`default_nettype none

module portb_emu (
    input  wire       phi2,       /* PHI2 bus clock (1.79 MHz)              */
    input  wire       pia_sel,    /* 1 when addr is in $D3xx                */
    input  wire [1:0] rs,         /* addr[1:0] register select              */
    input  wire [7:0] data_in,    /* data bus driven by the Atari (writes)  */
    input  wire       rw,         /* 1 = read, 0 = write                    */
    output reg  [7:0] portb,      /* PORTB output register                  */
    output reg  [7:0] pbctl,      /* PBCTL                                  */
    output wire [7:0] data_out,   /* data to drive onto Atari bus (reads)   */
    output wire       data_oe     /* 1 = drive data_out onto the Atari bus  */
);
    reg [7:0] ddrb;  /* data direction register (not visible externally)   */

    initial begin
        portb = 8'hFF;
        pbctl = 8'h00;
        ddrb  = 8'h00;
    end

    /* --- Write path: latch on PHI2 falling edge -------------------------*/
    always @(negedge phi2) begin
        if (!rw && pia_sel) begin
            case (rs)
                2'b01: begin   /* $D301 / mirrors */
                    if (pbctl[2]) portb <= data_in;
                    else          ddrb  <= data_in;
                end
                2'b11: begin   /* $D303 / mirrors */
                    pbctl <= data_in;
                end
                default: ;
            endcase
        end
    end

    /* --- Read path: purely combinational --------------------------------*/
    wire [7:0] d301_rd = pbctl[2] ? portb : ddrb;

    assign data_out = (rs == 2'b01) ? d301_rd : pbctl;

    /* Drive the Atari bus only for odd-addressed PIA registers during a
     * PHI2-high read cycle.  Both $D301 and $D303 have addr[0]=1. */
    assign data_oe  = phi2 && rw && pia_sel && rs[0];

endmodule

megaram/hw/rtl/top.v
/* top.v — ATARI XL/XE memory-expansion glue logic for CPLD / FPGA.
 *
 * ── Topology (Topology B — glue-logic only) ──────────────────────────────
 *
 * The SRAM data bus is wired DIRECTLY to the Atari data bus on the PCB via
 * 5V↔3.3V bidirectional level-shifters (e.g. TXS0108B).  The FPGA acts
 * only as glue logic: it provides the bank-mapped SRAM address and the SRAM
 * control signals (CE_N, OE_N, WE_N), and also emulates the PIA registers
 * ($D301/$D303) by driving the Atari data bus only for those reads.
 *
 * This matches the topology used by real ATARI memory-expansion boards
 * (RAMBO, Compyshop) where the SRAM is on the Atari bus, not behind a
 * separate FPGA-managed data path.
 *
 * ── Theory of operation ──────────────────────────────────────────────────
 *
 * The ATARI XE/XL computers perform banked-RAM access by writing to PORTB
 * ($D301) after setting PBCTL bit 2 ($D303).  The bank-window is the
 * 16 KB region $4000–$7FFF.  When the CPU accesses that window with the
 * appropriate PORTB value, the FPGA:
 *
 *   1. Asserts EXTSEL_N (active-low) to disable the Atari's internal RAM
 *      in $4000–$7FFF.
 *   2. Presents {bank, addr[13:0]} on the SRAM address bus.
 *   3. Controls SRAM_CE_N, SRAM_OE_N, SRAM_WE_N for the access.
 *      The SRAM data bus drives the Atari data bus directly (reads) or
 *      is driven by the Atari (writes) — the FPGA is not in the data path.
 *
 * Accesses to $D301/$D303 are intercepted to maintain the PORTB and PBCTL
 * shadow registers; the FPGA drives the Atari data bus only for those reads.
 *
 * ── Signal timing ─────────────────────────────────────────────────────────
 *
 *  ┌──────────┐      ┌──────────────────────────────┐
 *  │ PHI2     │      │  HIGH (~279 ns @ 1.79 MHz)   │
 * ─┘          └──────┘                              └────
 *  ← addr valid before PHI2 rise (6502 spec)
 *  ← SRAM_ADDR / CE_N / OE_N asserted combinationally when PHI2 rises
 *  ← SRAM data available within SRAM access time (10 ns for -10 chip)
 *  ← For writes: data valid from Atari during PHI2 high; WE_N = !PHI2·sel
 *  ← Registers (PORTB, PBCTL) updated on PHI2 falling edge
 *
 * ── SRAM sizing ───────────────────────────────────────────────────────────
 *
 *  The parameter SRAM_ADDR_BITS controls the SRAM address width:
 *    19 → AS7C38096A-10TIN  512 K × 8  (covers up to 576K expansion)
 *    20 → larger 1M × 8 chip           (required for 1088K expansion)
 *
 * ── Required tools ────────────────────────────────────────────────────────
 *
 *  Synthesis:  yosys   (https://yosyshq.net/yosys/)
 *  iCE40 P&R:  nextpnr-ice40 + icestorm
 *  ECP5  P&R:  nextpnr-ecp5  + prjtrellis
 */
`default_nettype none
`timescale 1ns/1ps

module top #(
    parameter SRAM_ADDR_BITS = 20   /* 19 for 512K SRAM, 20 for 1M SRAM */
)(
    /* ── Atari bus (all signals 5V; use level-shifters on the PCB) ──────*/
    input  wire        phi2,            /* PHI2 system clock (1.79 MHz)   */
    input  wire [15:0] addr,            /* address bus A0–A15              */
    inout  wire  [7:0] atari_data,      /* data bus D0–D7 (bidirectional)  */
    input  wire        rw,              /* 1 = read, 0 = write             */

    /* ── Expansion-type DIP switches (3 bits = 8 types) ────────────────*/
    input  wire  [2:0] conf,            /* CONF0=conf[0], CONF1, CONF2    */

    /* ── Atari control outputs ──────────────────────────────────────────*/
    output wire        extsel_n,        /* EXTSEL_N: disable internal RAM  */

    /* ── External SRAM — address and control only ───────────────────────
     * The SRAM data bus is wired directly to the Atari data bus on the PCB
     * via bidirectional level-shifters; no SRAM data pins on the FPGA.   */
    output wire [SRAM_ADDR_BITS-1:0] sram_addr,
    output wire        sram_ce_n,
    output wire        sram_oe_n,
    output wire        sram_we_n
);

    /* ── Address decode ─────────────────────────────────────────────────*/

    /* $4000–$7FFF: banked window (addr[15:14] == 2'b01) */
    wire is_window = (addr[15:14] == 2'b01);

    /* $D300–$D3FF: PIA area.
     * The Atari wires A0→RS1, A1→RS0 on the 6520 (reversed), so:
     *   addr[1:0] == 2'b01 → RS = 10 → PORTB / DDRB  ($D301, $D305 …)
     *   addr[1:0] == 2'b11 → RS = 11 → PBCTL / CRB   ($D303, $D307 …) */
    wire is_d3xx   = (addr[15:8] == 8'hD3);
    wire is_portb  = is_d3xx && (addr[1:0] == 2'b01);
    wire is_pbctl  = is_d3xx && (addr[1:0] == 2'b11);
    wire is_pia    = is_portb || is_pbctl;

    /* ── PORTB / PBCTL emulator ─────────────────────────────────────────*/
    wire [7:0] portb, pbctl;
    wire [7:0] pia_data_out;
    wire       pia_data_oe;

    portb_emu u_pia (
        .phi2     (phi2),
        .pia_sel  (is_pia),
        .rs       (addr[1:0]),
        .data_in  (atari_data),
        .rw       (rw),
        .portb    (portb),
        .pbctl    (pbctl),
        .data_out (pia_data_out),
        .data_oe  (pia_data_oe)
    );

    /* ── Bank decoder ───────────────────────────────────────────────────*/
    wire [5:0] bank;
    wire       ram_active;

    bank_switch u_bsw (
        .portb      (portb),
        .pbctl_crb2 (pbctl[2]),
        .conf       (conf),
        .bank       (bank),
        .active     (ram_active)
    );

    /* ── SRAM control ───────────────────────────────────────────────────*/

    /* A cycle hits the external SRAM when: PHI2 high, address in window,
     * ram_active (PORTB / PBCTL configured correctly for this type). */
    wire sram_sel = phi2 && is_window && ram_active;
    wire sram_rd  = sram_sel &&  rw;
    wire sram_wr  = sram_sel && !rw;

    /* SRAM address: upper (SRAM_ADDR_BITS-14) bits = bank LSBs,
     * lower 14 bits = offset within the 16K window.
     * For a 512K SRAM (SRAM_ADDR_BITS=19) only bank[4:0] is used;
     * for a 1M SRAM (SRAM_ADDR_BITS=20) all bank[5:0] bits are used. */
    assign sram_addr = {bank[SRAM_ADDR_BITS-15:0], addr[13:0]};

    assign sram_ce_n = !sram_sel;
    assign sram_oe_n = !sram_rd;
    /* WE_N is active during the whole PHI2-high write period, which gives
     * the SRAM the maximum data-setup time. */
    assign sram_we_n = !sram_wr;

    /* ── Data-bus management ────────────────────────────────────────────
     * The FPGA drives the Atari data bus ONLY for PIA register reads
     * ($D301 / $D303).  For SRAM reads the SRAM chip drives the bus
     * directly (SRAM_OE_N low); the FPGA must tristate. */
    assign atari_data = pia_data_oe ? pia_data_out : 8'hZZ;

    /* ── EXTSEL_N ────────────────────────────────────────────────────────
     * Assert (low) to disable Atari's own $4000–$7FFF SRAM whenever we
     * are serving the cycle from external SRAM. */
    assign extsel_n = !sram_sel;

endmodule

megaram/hw/sim/tb_top.v
/* tb_top.v — Simulation testbench for the ATARI memory-expansion top module.
 *
 * Topology B: SRAM data bus is wired directly to the Atari data bus.
 * The testbench models this by having the SRAM model drive/receive from
 * atari_data (the shared bus), not a separate sram_data wire.
 *
 * Tests:
 *   1. Write PBCTL ($D303) to enable output-register mode (bit 2 = 1).
 *   2. Write PORTB ($D301) to select bank 3 (130XE conf) → bank_r = 3.
 *   3. Read  from banked window ($5000) → check SRAM address & control.
 *   4. Write to banked window ($5000) → check SRAM write pulse.
 *   5. Write PORTB with CBE=1 (bit4=1) → SRAM must not respond.
 *   6. 256K_RAMBO: RAME=1 (bit4=1) → SRAM must not respond.
 *
 * Run with:  iverilog -g2005-sv -o tb tb_top.v rtl/top.v rtl/portb_emu.v \
 *                     rtl/bank_switch.v && vvp tb
 */
`default_nettype none
`timescale 1ns/1ps

module tb_top;

    /* ── DUT signals ────────────────────────────────────────────────────*/
    reg        phi2;
    reg [15:0] addr;
    wire [7:0] atari_data;
    reg        rw;
    reg  [2:0] conf;
    wire       extsel_n;
    wire [19:0] sram_addr;
    wire        sram_ce_n, sram_oe_n, sram_we_n;

    reg [7:0] atari_data_drive;
    reg       atari_data_en;

    /* Atari CPU drives the bus during write cycles */
    assign atari_data = atari_data_en ? atari_data_drive : 8'hZZ;

    /* Minimal SRAM model: 512K × 8.
     * Topology B: SRAM data is on the Atari data bus.
     * Drive atari_data during reads; latch from atari_data on WE_N negedge. */
    reg [7:0] sram_mem [0:524287];
    assign atari_data = (!sram_ce_n && !sram_oe_n && sram_we_n)
                        ? sram_mem[sram_addr[18:0]] : 8'hZZ;
    always @(negedge sram_we_n)
        if (!sram_ce_n) sram_mem[sram_addr[18:0]] <= atari_data;

    /* ── DUT instantiation ──────────────────────────────────────────────*/
    top #(.SRAM_ADDR_BITS(20)) dut (
        .phi2      (phi2),
        .addr      (addr),
        .atari_data(atari_data),
        .rw        (rw),
        .conf      (conf),
        .extsel_n  (extsel_n),
        .sram_addr (sram_addr),
        .sram_ce_n (sram_ce_n),
        .sram_oe_n (sram_oe_n),
        .sram_we_n (sram_we_n)
    );

    /* ── Clock: PHI2 at 1.79 MHz (period ≈ 559 ns) ─────────────────────*/
    initial phi2 = 0;
    always #279 phi2 = ~phi2;

    /* ── Helper tasks ───────────────────────────────────────────────────*/

    /* One full PHI2 write bus cycle */
    task bus_write;
        input [15:0] a;
        input  [7:0] d;
        begin
            @(negedge phi2);        /* start on PHI2 low */
            addr           = a;
            atari_data_drive = d;
            atari_data_en  = 1;
            rw             = 0;
            @(posedge phi2);        /* PHI2 rises: cycle begins */
            @(negedge phi2);        /* PHI2 falls: DUT latches */
            #5;
            atari_data_en = 0;
            rw = 1;
        end
    endtask

    /* One full PHI2 read bus cycle; returns sampled data in rd_data */
    task bus_read;
        input  [15:0] a;
        output  [7:0] rd;
        begin
            @(negedge phi2);
            addr          = a;
            atari_data_en = 0;
            rw            = 1;
            @(posedge phi2);
            #50;                    /* wait for combinational propagation */
            rd = atari_data;
            @(negedge phi2);
            #5;
        end
    endtask

    /* ── Stimulus ───────────────────────────────────────────────────────*/
    integer errors;
    reg [7:0] rd;

    initial begin
        $dumpfile("tb_top.vcd");
        $dumpvars(0, tb_top);

        phi2          = 0;
        addr          = 16'h0000;
        rw            = 1;
        atari_data_en = 0;
        conf          = 3'd0;       /* 130XE */
        errors        = 0;

        /* Seed the SRAM with known pattern */
        sram_mem[20'h01000] = 8'hAB;

        /* ── TEST 1: PBCTL write (enable output register mode) ──────────*/
        #100;
        bus_write(16'hD303, 8'h3C);  /* PBCTL = 0x3C: bit2=1 */
        #50;
        if (dut.u_pia.pbctl !== 8'h3C) begin
            $display("FAIL T1: PBCTL expected 0x3C got 0x%02x", dut.u_pia.pbctl);
            errors = errors + 1;
        end else $display("PASS T1: PBCTL=0x3C");

        /* ── TEST 2: PORTB write → bank 3 (bits 3:2 = 11) ──────────────*/
        bus_write(16'hD301, 8'hEC);  /* portb = 0b11101100 → bits[3:2]=11 → bank=3; bit4=0 */
        #50;
        if (dut.u_pia.portb !== 8'hEC) begin
            $display("FAIL T2: PORTB expected 0xEC got 0x%02x", dut.u_pia.portb);
            errors = errors + 1;
        end else $display("PASS T2: PORTB=0xEC");
        if (dut.bank !== 6'd3) begin
            $display("FAIL T2b: bank expected 3 got %0d", dut.bank);
            errors = errors + 1;
        end else $display("PASS T2b: bank=3");

        /* ── TEST 3: Read from banked window → check SRAM address/control ─
         * Expected SRAM addr = bank(3)<<14 | ($5000 & $3FFF) = $C000|$1000 = $D000
         * Control signals are sampled while PHI2 is still high. */
        @(negedge phi2);
        addr = 16'h5000; rw = 1; atari_data_en = 0;
        @(posedge phi2); #50;          /* sample mid-cycle while PHI2 high */
        if (sram_ce_n !== 1'b0) begin
            $display("FAIL T3: SRAM_CE_N should be 0 during window read");
            errors = errors + 1;
        end else $display("PASS T3: SRAM_CE_N=0");
        if (sram_oe_n !== 1'b0) begin
            $display("FAIL T3b: SRAM_OE_N should be 0 during window read");
            errors = errors + 1;
        end else $display("PASS T3b: SRAM_OE_N=0");
        if (extsel_n !== 1'b0) begin
            $display("FAIL T3c: EXTSEL_N should be 0 during window read");
            errors = errors + 1;
        end else $display("PASS T3c: EXTSEL_N=0");
        $display("     SRAM_ADDR=0x%05X (expected 0x0D000)", sram_addr);
        @(negedge phi2); #5; rw = 1;

        /* ── TEST 4: Write to banked window → check WE_N pulse ──────────*/
        bus_write(16'h5000, 8'h55);
        #50;
        if (sram_mem[20'h0D000] !== 8'h55) begin
            $display("FAIL T4: SRAM[0x0D000] expected 0x55 got 0x%02x", sram_mem[20'h0D000]);
            errors = errors + 1;
        end else $display("PASS T4: SRAM write 0x55 at 0x0D000");

        /* ── TEST 5: CBE=1 (bit4=1) → SRAM must not respond ────────────*/
        bus_write(16'hD301, 8'hFC);  /* portb[4]=1 → CBE set → no external RAM */
        #50;
        @(negedge phi2);
        addr = 16'h5000; rw = 1; atari_data_en = 0;
        @(posedge phi2); #50;
        if (sram_ce_n !== 1'b1) begin
            $display("FAIL T5: SRAM_CE_N should be 1 when CBE=1");
            errors = errors + 1;
        end else $display("PASS T5: SRAM_CE_N=1 with CBE=1 (no ext RAM)");
        if (extsel_n !== 1'b1) begin
            $display("FAIL T5b: EXTSEL_N should be 1 when CBE=1");
            errors = errors + 1;
        end else $display("PASS T5b: EXTSEL_N=1");
        @(negedge phi2); rw = 1;

        /* ── TEST 6: 256K_RAMBO — RAME=1 (bit4=1) must block access ────*/
        conf = 3'd2;  /* EXP_256K_RAMBO */
        bus_write(16'hD303, 8'h04);  /* PBCTL[2]=1 */
        bus_write(16'hD301, 8'hF0);  /* portb[4]=1 → RAME=1 → disabled */
        @(negedge phi2);
        addr = 16'h5000; rw = 1; atari_data_en = 0;
        @(posedge phi2); #50;
        if (sram_ce_n !== 1'b1) begin
            $display("FAIL T6: SRAM_CE_N should be 1 when RAME=1 (256K_RAMBO)");
            errors = errors + 1;
        end else $display("PASS T6: SRAM_CE_N=1 with RAME=1 (256K_RAMBO disabled)");
        @(negedge phi2);

        /* ── RESULT ──────────────────────────────────────────────────────*/
        #200;
        if (errors == 0)
            $display("\n*** ALL TESTS PASSED ***");
        else
            $display("\n*** %0d TEST(S) FAILED ***", errors);
        $finish;
    end

    /* Timeout watchdog */
    initial begin
        #500000;
        $display("TIMEOUT");
        $finish;
    end

endmodule

megaram/hw/build/sim/tb_top.vcd
$date
	Mon Jun 29 12:33:32 2026
$end
$version
	Icarus Verilog
$end
$timescale
	1ps
$end
$scope module tb_top $end
$var wire 8 ! atari_data [7:0] $end
$var wire 1 " sram_we_n $end
$var wire 1 # sram_oe_n $end
$var wire 1 $ sram_ce_n $end
$var wire 20 % sram_addr [19:0] $end
$var wire 1 & extsel_n $end
$var reg 16 ' addr [15:0] $end
$var reg 8 ( atari_data_drive [7:0] $end
$var reg 1 ) atari_data_en $end
$var reg 3 * conf [2:0] $end
$var reg 1 + phi2 $end
$var reg 1 , rw $end
$var integer 32 - errors [31:0] $end
$scope module dut $end
$var wire 16 . addr [15:0] $end
$var wire 8 / atari_data [7:0] $end
$var wire 3 0 conf [2:0] $end
$var wire 1 1 is_pbctl $end
$var wire 1 2 is_pia $end
$var wire 1 3 is_portb $end
$var wire 1 + phi2 $end
$var wire 1 , rw $end
$var wire 1 4 sram_rd $end
$var wire 1 5 sram_sel $end
$var wire 1 6 sram_wr $end
$var wire 1 " sram_we_n $end
$var wire 1 # sram_oe_n $end
$var wire 1 $ sram_ce_n $end
$var wire 20 7 sram_addr [19:0] $end
$var wire 1 8 ram_active $end
$var wire 8 9 portb [7:0] $end
$var wire 8 : pia_data_out [7:0] $end
$var wire 1 ; pia_data_oe $end
$var wire 8 < pbctl [7:0] $end
$var wire 1 = is_window $end
$var wire 1 > is_d3xx $end
$var wire 1 & extsel_n $end
$var wire 6 ? bank [5:0] $end
$scope module u_bsw $end
$var wire 3 @ conf [2:0] $end
$var wire 1 A pbctl_crb2 $end
$var wire 8 B portb [7:0] $end
$var wire 6 C bank [5:0] $end
$var wire 1 8 active $end
$var reg 1 8 active_r $end
$var reg 6 D bank_r [5:0] $end
$upscope $end
$scope module u_pia $end
$var wire 8 E data_in [7:0] $end
$var wire 1 ; data_oe $end
$var wire 1 + phi2 $end
$var wire 1 2 pia_sel $end
$var wire 2 F rs [1:0] $end
$var wire 1 , rw $end
$var wire 8 G data_out [7:0] $end
$var wire 8 H d301_rd [7:0] $end
$var reg 8 I ddrb [7:0] $end
$var reg 8 J pbctl [7:0] $end
$var reg 8 K portb [7:0] $end
$upscope $end
$upscope $end
$scope task bus_read $end
$var reg 16 L a [15:0] $end
$var reg 8 M rd [7:0] $end
$upscope $end
$scope task bus_write $end
$var reg 16 N a [15:0] $end
$var reg 8 O d [7:0] $end
$upscope $end
$upscope $end
$enddefinitions $end
#0
$dumpvars
bx O
bx N
bx M
bx L
b11111111 K
b0 J
b0 I
b0 H
b0 G
b0 F
bz E
b0 D
b0 C
b11111111 B
0A
b0 @
b0 ?
0>
0=
b0 <
0;
b0 :
b11111111 9
08
b0 7
06
05
04
03
02
01
b0 0
bz /
b0 .
b0 -
1,
0+
b0 *
0)
bx (
b0 '
1&
b0 %
1$
1#
1"
bz !
$end
#100000
b111100 O
b1101001100000011 N
#279000
1+
#558000
12
11
b111100 !
b111100 /
b111100 E
1>
b11 F
b1001100000011 %
b1001100000011 7
0,
1)
b111100 (
b1101001100000011 '
b1101001100000011 .
0+
#837000
1+
#1116000
b11111111 H
b111100 :
b111100 G
1A
b111100 <
b111100 J
0+
#1121000
bz !
bz /
bz E
1,
0)
#1171000
b11101100 O
b1101001100000001 N
#1395000
b111100 !
b111100 /
b111100 E
1;
1+
#1674000
0;
13
01
b11111111 :
b11111111 G
b11101100 !
b11101100 /
b11101100 E
b1 F
b1001100000001 %
b1001100000001 7
0,
1)
b11101100 (
b1101001100000001 '
b1101001100000001 .
0+
#1953000
1+
#2232000
b11101100 :
b11101100 G
b11101100 H
18
b1101001100000001 %
b1101001100000001 7
b11 ?
b11 C
b11 D
b11101100 9
b11101100 B
b11101100 K
0+
#2237000
bz !
bz /
bz E
1,
0)
#2511000
b11101100 !
b11101100 /
b11101100 E
1;
1+
#2790000
02
bz !
bz /
bz E
0;
03
b111100 :
b111100 G
1=
0>
b0 F
b1101000000000000 %
b1101000000000000 7
b101000000000000 '
b101000000000000 .
0+
#3069000
bx !
bx /
bx E
0#
14
0$
0&
15
1+
#3348000
bz !
bz /
bz E
1#
04
1$
1&
05
0+
#3353000
b1010101 O
b101000000000000 N
#3627000
bx !
bx /
bx E
0#
14
0$
0&
15
1+
#3906000
b1010101 !
b1010101 /
b1010101 E
1$
1&
05
1#
04
1"
06
0,
1)
b1010101 (
0+
#4185000
0"
16
0$
0&
15
1+
#4464000
1"
06
1$
1&
05
0+
#4469000
bz !
bz /
bz E
1,
0)
#4519000
b11111100 O
b1101001100000001 N
#4743000
b1010101 !
b1010101 /
b1010101 E
0#
14
0$
0&
15
1+
#5022000
12
13
b11101100 :
b11101100 G
1$
1&
05
1#
04
1"
06
b11111100 !
b11111100 /
b11111100 E
0=
1>
b1 F
b1101001100000001 %
b1101001100000001 7
0,
1)
b11111100 (
b1101001100000001 '
b1101001100000001 .
0+
#5301000
1+
#5580000
b11111100 :
b11111100 G
b11111100 H
08
b1001100000001 %
b1001100000001 7
b0 ?
b0 C
b0 D
b11111100 9
b11111100 B
b11111100 K
0+
#5585000
bz !
bz /
bz E
1,
0)
#5859000
b11111100 !
b11111100 /
b11111100 E
1;
1+
#6138000
02
bz !
bz /
bz E
0;
03
b111100 :
b111100 G
1=
0>
b0 F
b1000000000000 %
b1000000000000 7
b101000000000000 '
b101000000000000 .
0+
#6417000
1+
#6696000
b100 O
b1101001100000011 N
b10 *
b10 0
b10 @
0+
#6975000
1+
#7254000
12
11
b100 !
b100 /
b100 E
0=
1>
b11 F
b1001100000011 %
b1001100000011 7
0,
1)
b100 (
b1101001100000011 '
b1101001100000011 .
0+
#7533000
1+
#7812000
b100 :
b100 G
b100 <
b100 J
0+
#7817000
bz !
bz /
bz E
b11110000 O
b1101001100000001 N
1,
0)
#8091000
b100 !
b100 /
b100 E
1;
1+
#8370000
0;
13
01
b11111100 :
b11111100 G
b11110000 !
b11110000 /
b11110000 E
b1 F
b1001100000001 %
b1001100000001 7
0,
1)
b11110000 (
b1101001100000001 '
b1101001100000001 .
0+
#8649000
1+
#8928000
b11110000 :
b11110000 G
b11110000 H
b11110000 9
b11110000 B
b11110000 K
0+
#8933000
bz !
bz /
bz E
1,
0)
#9207000
b11110000 !
b11110000 /
b11110000 E
1;
1+
#9486000
02
bz !
bz /
bz E
0;
03
b100 :
b100 G
1=
0>
b0 F
b1000000000000 %
b1000000000000 7
b101000000000000 '
b101000000000000 .
0+
#9765000
1+
#10044000
0+
